odoo/addons/base_optional_quick_create/README.rst
odoo/addons/base_optional_quick_create/__init__.py
odoo/addons/base_optional_quick_create/__manifest__.py
odoo/addons/base_optional_quick_create/i18n/base_optional_quick_create.pot
odoo/addons/base_optional_quick_create/i18n/de.po
odoo/addons/base_optional_quick_create/i18n/es.po
odoo/addons/base_optional_quick_create/i18n/fi.po
odoo/addons/base_optional_quick_create/i18n/fr.po
odoo/addons/base_optional_quick_create/i18n/hr.po
odoo/addons/base_optional_quick_create/i18n/hr_HR.po
odoo/addons/base_optional_quick_create/i18n/it.po
odoo/addons/base_optional_quick_create/i18n/nb_NO.po
odoo/addons/base_optional_quick_create/i18n/pt_BR.po
odoo/addons/base_optional_quick_create/i18n/sl.po
odoo/addons/base_optional_quick_create/i18n/tr.po
odoo/addons/base_optional_quick_create/i18n/tr_TR.po
odoo/addons/base_optional_quick_create/i18n/zh_CN.po
odoo/addons/base_optional_quick_create/models/__init__.py
odoo/addons/base_optional_quick_create/models/ir_model.py
odoo/addons/base_optional_quick_create/readme/CONTRIBUTORS.rst
odoo/addons/base_optional_quick_create/readme/CREDITS.rst
odoo/addons/base_optional_quick_create/readme/DESCRIPTION.rst
odoo/addons/base_optional_quick_create/readme/USAGE.rst
odoo/addons/base_optional_quick_create/static/description/icon.png
odoo/addons/base_optional_quick_create/static/description/index.html
odoo/addons/base_optional_quick_create/tests/__init__.py
odoo/addons/base_optional_quick_create/tests/test_quick_create.py
odoo/addons/base_optional_quick_create/views/model_view.xml
odoo14_addon_base_optional_quick_create-14.0.1.0.1.dev7.dist-info/METADATA
odoo14_addon_base_optional_quick_create-14.0.1.0.1.dev7.dist-info/WHEEL
odoo14_addon_base_optional_quick_create-14.0.1.0.1.dev7.dist-info/top_level.txt
odoo14_addon_base_optional_quick_create-14.0.1.0.1.dev7.dist-info/RECORD
